lsst/ts/IntegrationTests/__init__.py
lsst/ts/IntegrationTests/aux_tel_visit.py
lsst/ts/IntegrationTests/base_script.py
lsst/ts/IntegrationTests/config_registry.py
lsst/ts/IntegrationTests/script_queue_controller.py
lsst/ts/IntegrationTests/take_image_latiss_configs.py
lsst/ts/IntegrationTests/testutils.py
lsst/ts/IntegrationTests/version.py
lsst/ts/IntegrationTests/yaml_test_strings.py
ts_IntegrationTests-0.1.1.data/scripts/auxtel_visit.py
ts_IntegrationTests-0.1.1.data/scripts/simple_script.py
ts_IntegrationTests-0.1.1.dist-info/LICENSE
ts_IntegrationTests-0.1.1.dist-info/METADATA
ts_IntegrationTests-0.1.1.dist-info/WHEEL
ts_IntegrationTests-0.1.1.dist-info/top_level.txt
ts_IntegrationTests-0.1.1.dist-info/RECORD
