Metadata-Version: 2.1
Name: ts-IntegrationTests
Version: 0.1.1
Summary: TSSW integration test scripts.
Home-page: UNKNOWN
License: GPL
Project-URL: Bug Tracker, https://jira.lsstcorp.org/secure/Dashboard.jspa
Project-URL: Source Code, https://github.com/lsst-ts/ts_IntegrationTests
Platform: UNKNOWN
